[
  {
    "id": "2423785397",
    "etr": "2022-09-01T22:15:00Z",
    "etrConfidence": null,
    "cluster": false,
    "comments": "We show your power is out at this location. Your estimated repair time is currently Sep 01, 2022, 5:15 PM Central. We are working to identify the problem.",
    "cause": null,
    "numberOut": 1,
    "custAffected": 4,
    "crewStatus": null,
    "startTime": null,
    "latitude": 32.34956,
    "longitude": -86.21323,
    "source": "https://kubra.io/cluster-data/032/5182a906-9bd4-45db-9507-dd11d2e3ae0c/019c7993-c647-4b35-bd91-98991348d802/public/cluster-1/0320023230.json"
  },
  {
    "id": "2433788544",
    "etr": "2022-09-01T01:00:00Z",
    "etrConfidence": null,
    "cluster": false,
    "comments": "A fallen tree has caused an outage in your area. We are working to restore power as quickly and safely as possible. Your estimated repair time for this location is currently Aug 31, 2022, 8:00 PM Central.",
    "cause": null,
    "numberOut": 1,
    "custAffected": 24,
    "crewStatus": null,
    "startTime": null,
    "latitude": 32.37542,
    "longitude": -86.23869,
    "source": "https://kubra.io/cluster-data/032/5182a906-9bd4-45db-9507-dd11d2e3ae0c/019c7993-c647-4b35-bd91-98991348d802/public/cluster-1/0320023230.json"
  },
  {
    "id": "2433788477",
    "etr": "2022-09-01T05:00:00Z",
    "etrConfidence": null,
    "cluster": false,
    "comments": "We show your power is out at this location. Your estimated repair time is currently Sep 01, 2022, 12:00 AM Central. We are working to identify the problem.",
    "cause": null,
    "numberOut": 1,
    "custAffected": 4,
    "crewStatus": null,
    "startTime": null,
    "latitude": 33.69346,
    "longitude": -85.53415,
    "source": "https://kubra.io/cluster-data/320/5182a906-9bd4-45db-9507-dd11d2e3ae0c/019c7993-c647-4b35-bd91-98991348d802/public/cluster-1/0320023.json"
  },
  {
    "id": "2433788604",
    "etr": "2022-09-01T02:00:00Z",
    "etrConfidence": null,
    "cluster": false,
    "comments": "We show your power is out at this location. Your estimated repair time is currently Aug 31, 2022, 9:00 PM Central. We are working to identify the problem.",
    "cause": null,
    "numberOut": 1,
    "custAffected": 4,
    "crewStatus": null,
    "startTime": null,
    "latitude": 33.61722,
    "longitude": -85.92137,
    "source": "https://kubra.io/cluster-data/320/5182a906-9bd4-45db-9507-dd11d2e3ae0c/019c7993-c647-4b35-bd91-98991348d802/public/cluster-1/0320023.json"
  },
  {
    "id": "2433788021",
    "etr": "ETR-EXP",
    "etrConfidence": null,
    "cluster": false,
    "comments": "Field personnel are on their way to evaluate the outage in your area. Your estimated repair time for this location is currently unavailable. As the outage is evaluated, this message will be updated.",
    "cause": null,
    "numberOut": 1,
    "custAffected": 4,
    "crewStatus": null,
    "startTime": null,
    "latitude": 33.62115,
    "longitude": -86.46668,
    "source": "https://kubra.io/cluster-data/030/5182a906-9bd4-45db-9507-dd11d2e3ae0c/019c7993-c647-4b35-bd91-98991348d802/public/cluster-1/0320023030.json"
  },
  {
    "id": "2433788616",
    "etr": "2022-09-01T02:30:00Z",
    "etrConfidence": null,
    "cluster": false,
    "comments": "Field personnel are on their way to evaluate the outage in your area. Your estimated repair time for this location is currently Aug 31, 2022, 9:30 PM Central. As the outage is evaluated, this message will be updated.",
    "cause": null,
    "numberOut": 1,
    "custAffected": 4,
    "crewStatus": null,
    "startTime": null,
    "latitude": 33.53709,
    "longitude": -86.2062,
    "source": "https://kubra.io/cluster-data/320/5182a906-9bd4-45db-9507-dd11d2e3ae0c/019c7993-c647-4b35-bd91-98991348d802/public/cluster-1/0320023.json"
  },
  {
    "id": "2433788579",
    "etr": "2022-09-01T01:30:00Z",
    "etrConfidence": null,
    "cluster": false,
    "comments": "Field personnel are on their way to evaluate the outage in your area. Your estimated repair time for this location is currently Aug 31, 2022, 8:30 PM Central. As the outage is evaluated, this message will be updated.",
    "cause": null,
    "numberOut": 1,
    "custAffected": 4,
    "crewStatus": null,
    "startTime": null,
    "latitude": 33.7538,
    "longitude": -88.11049,
    "source": "https://kubra.io/cluster-data/220/5182a906-9bd4-45db-9507-dd11d2e3ae0c/019c7993-c647-4b35-bd91-98991348d802/public/cluster-1/0320022.json"
  },
  {
    "id": "2433788561",
    "etr": "2022-09-01T01:00:00Z",
    "etrConfidence": null,
    "cluster": false,
    "comments": "Field personnel are on site evaluating the outage in your area. The cause of the outage is not yet determined. Your estimated repair time for this location is currently Aug 31, 2022, 8:00 PM Central.",
    "cause": null,
    "numberOut": 1,
    "custAffected": 4,
    "crewStatus": null,
    "startTime": null,
    "latitude": 33.95641,
    "longitude": -87.56808,
    "source": "https://kubra.io/cluster-data/220/5182a906-9bd4-45db-9507-dd11d2e3ae0c/019c7993-c647-4b35-bd91-98991348d802/public/cluster-1/0320022.json"
  },
  {
    "id": "2433788580",
    "etr": "2022-09-01T01:30:00Z",
    "etrConfidence": null,
    "cluster": false,
    "comments": "Field personnel are on their way to evaluate the outage in your area. Your estimated repair time for this location is currently Aug 31, 2022, 8:30 PM Central. As the outage is evaluated, this message will be updated.",
    "cause": null,
    "numberOut": 1,
    "custAffected": 4,
    "crewStatus": null,
    "startTime": null,
    "latitude": 34.08808,
    "longitude": -87.31012,
    "source": "https://kubra.io/cluster-data/220/5182a906-9bd4-45db-9507-dd11d2e3ae0c/019c7993-c647-4b35-bd91-98991348d802/public/cluster-1/0320022.json"
  },
  {
    "id": "2433788602",
    "etr": "2022-09-01T02:00:00Z",
    "etrConfidence": null,
    "cluster": false,
    "comments": "Field personnel are on their way to evaluate the outage in your area. Your estimated repair time for this location is currently Aug 31, 2022, 9:00 PM Central. As the outage is evaluated, this message will be updated.",
    "cause": null,
    "numberOut": 1,
    "custAffected": 4,
    "crewStatus": null,
    "startTime": null,
    "latitude": 32.84187,
    "longitude": -87.90714,
    "source": "https://kubra.io/cluster-data/220/5182a906-9bd4-45db-9507-dd11d2e3ae0c/019c7993-c647-4b35-bd91-98991348d802/public/cluster-1/0320022.json"
  },
  {
    "id": "2433788597",
    "etr": "2022-09-01T02:00:00Z",
    "etrConfidence": null,
    "cluster": false,
    "comments": "Field personnel have been assigned to evaluate the outage in your area. Your estimated repair time for this location is currently Aug 31, 2022, 9:00 PM Central. As the outage is evaluated, this message will be updated. ",
    "cause": null,
    "numberOut": 1,
    "custAffected": 4,
    "crewStatus": null,
    "startTime": null,
    "latitude": 33.70425,
    "longitude": -87.81938,
    "source": "https://kubra.io/cluster-data/220/5182a906-9bd4-45db-9507-dd11d2e3ae0c/019c7993-c647-4b35-bd91-98991348d802/public/cluster-1/0320022.json"
  },
  {
    "id": "2433788572",
    "etr": "2022-09-01T01:30:00Z",
    "etrConfidence": null,
    "cluster": false,
    "comments": "Field personnel have been assigned to evaluate the outage in your area. Your estimated repair time for this location is currently Aug 31, 2022, 8:30 PM Central. As the outage is evaluated, this message will be updated. ",
    "cause": null,
    "numberOut": 1,
    "custAffected": 4,
    "crewStatus": null,
    "startTime": null,
    "latitude": 33.27808,
    "longitude": -87.03428,
    "source": "https://kubra.io/cluster-data/032/5182a906-9bd4-45db-9507-dd11d2e3ae0c/019c7993-c647-4b35-bd91-98991348d802/public/cluster-1/03200230.json"
  },
  {
    "id": "2433788615",
    "etr": "2022-09-01T02:30:00Z",
    "etrConfidence": null,
    "cluster": false,
    "comments": "Field personnel have been assigned to evaluate the outage in your area. Your estimated repair time for this location is currently Aug 31, 2022, 9:30 PM Central. As the outage is evaluated, this message will be updated. ",
    "cause": null,
    "numberOut": 1,
    "custAffected": 4,
    "crewStatus": null,
    "startTime": null,
    "latitude": 33.24213,
    "longitude": -86.82425,
    "source": "https://kubra.io/cluster-data/032/5182a906-9bd4-45db-9507-dd11d2e3ae0c/019c7993-c647-4b35-bd91-98991348d802/public/cluster-1/03200230.json"
  },
  {
    "id": "2433788548",
    "etr": "2022-09-01T01:00:00Z",
    "etrConfidence": null,
    "cluster": false,
    "comments": "Field personnel are on site evaluating the outage in your area. The cause of the outage is not yet determined. Your estimated repair time for this location is currently Aug 31, 2022, 8:00 PM Central.",
    "cause": null,
    "numberOut": 1,
    "custAffected": 4,
    "crewStatus": null,
    "startTime": null,
    "latitude": 33.51283,
    "longitude": -87.14821,
    "source": "https://kubra.io/cluster-data/032/5182a906-9bd4-45db-9507-dd11d2e3ae0c/019c7993-c647-4b35-bd91-98991348d802/public/cluster-1/03200230.json"
  },
  {
    "id": "2433788609",
    "etr": "2022-09-01T02:30:00Z",
    "etrConfidence": null,
    "cluster": false,
    "comments": "We show your power is out at this location. Your estimated repair time is currently Aug 31, 2022, 9:30 PM Central. We are working to identify the problem.",
    "cause": null,
    "numberOut": 1,
    "custAffected": 4,
    "crewStatus": null,
    "startTime": null,
    "latitude": 33.43864,
    "longitude": -86.79201,
    "source": "https://kubra.io/cluster-data/203/5182a906-9bd4-45db-9507-dd11d2e3ae0c/019c7993-c647-4b35-bd91-98991348d802/public/cluster-1/032002302.json"
  },
  {
    "id": "2433787751",
    "etr": "ETR-EXP",
    "etrConfidence": null,
    "cluster": false,
    "comments": "We are currently making upgrades or repairs to the system in your area. Your power at this location may be disrupted during this time. We expect to be finished in your area by unavailable.",
    "cause": null,
    "numberOut": 1,
    "custAffected": 4,
    "crewStatus": null,
    "startTime": null,
    "latitude": 33.46609,
    "longitude": -86.71944,
    "source": "https://kubra.io/cluster-data/321/5182a906-9bd4-45db-9507-dd11d2e3ae0c/019c7993-c647-4b35-bd91-98991348d802/public/cluster-1/032002302123.json"
  },
  {
    "id": "2433788583",
    "etr": "2022-09-01T02:00:00Z",
    "etrConfidence": null,
    "cluster": false,
    "comments": "Field personnel have been assigned to evaluate the outage in your area. Your estimated repair time for this location is currently Aug 31, 2022, 9:00 PM Central. As the outage is evaluated, this message will be updated. ",
    "cause": null,
    "numberOut": 1,
    "custAffected": 4,
    "crewStatus": null,
    "startTime": null,
    "latitude": 33.47227,
    "longitude": -86.73305,
    "source": "https://kubra.io/cluster-data/321/5182a906-9bd4-45db-9507-dd11d2e3ae0c/019c7993-c647-4b35-bd91-98991348d802/public/cluster-1/032002302123.json"
  },
  {
    "id": "2433788608",
    "etr": "2022-09-01T02:30:00Z",
    "etrConfidence": null,
    "cluster": false,
    "comments": "We show your power is out at this location. Your estimated repair time is currently Aug 31, 2022, 9:30 PM Central. We are working to identify the problem.",
    "cause": null,
    "numberOut": 1,
    "custAffected": 321,
    "crewStatus": null,
    "startTime": null,
    "latitude": 33.55493,
    "longitude": -86.55792,
    "source": "https://kubra.io/cluster-data/312/5182a906-9bd4-45db-9507-dd11d2e3ae0c/019c7993-c647-4b35-bd91-98991348d802/public/cluster-1/03200230213.json"
  },
  {
    "id": "2433788598",
    "etr": "2022-09-01T02:00:00Z",
    "etrConfidence": null,
    "cluster": false,
    "comments": "Field personnel have been assigned to evaluate the outage in your area. Your estimated repair time for this location is currently Aug 31, 2022, 9:00 PM Central. As the outage is evaluated, this message will be updated. ",
    "cause": null,
    "numberOut": 1,
    "custAffected": 4,
    "crewStatus": null,
    "startTime": null,
    "latitude": 33.52082,
    "longitude": -86.55517,
    "source": "https://kubra.io/cluster-data/312/5182a906-9bd4-45db-9507-dd11d2e3ae0c/019c7993-c647-4b35-bd91-98991348d802/public/cluster-1/03200230213.json"
  },
  {
    "id": "2433788603",
    "etr": "2022-09-01T02:00:00Z",
    "etrConfidence": null,
    "cluster": false,
    "comments": "Field personnel are on their way to evaluate the outage in your area. Your estimated repair time for this location is currently Aug 31, 2022, 9:00 PM Central. As the outage is evaluated, this message will be updated.",
    "cause": null,
    "numberOut": 1,
    "custAffected": 4,
    "crewStatus": null,
    "startTime": null,
    "latitude": 32.37605,
    "longitude": -87.38811,
    "source": "https://kubra.io/cluster-data/220/5182a906-9bd4-45db-9507-dd11d2e3ae0c/019c7993-c647-4b35-bd91-98991348d802/public/cluster-1/0320022.json"
  },
  {
    "id": "2413783687",
    "etr": "ETR-EXP",
    "etrConfidence": null,
    "cluster": false,
    "comments": "We show your power is out at this location. Your estimated repair time is currently unavailable. We are working to identify the problem.",
    "cause": null,
    "numberOut": 1,
    "custAffected": 4,
    "crewStatus": null,
    "startTime": null,
    "latitude": 32.79632,
    "longitude": -86.8802,
    "source": "https://kubra.io/cluster-data/320/5182a906-9bd4-45db-9507-dd11d2e3ae0c/019c7993-c647-4b35-bd91-98991348d802/public/cluster-1/0320023.json"
  },
  {
    "id": "2433788611",
    "etr": "2022-09-01T02:30:00Z",
    "etrConfidence": null,
    "cluster": false,
    "comments": "Field personnel are on their way to evaluate the outage in your area. Your estimated repair time for this location is currently Aug 31, 2022, 9:30 PM Central. As the outage is evaluated, this message will be updated.",
    "cause": null,
    "numberOut": 1,
    "custAffected": 4,
    "crewStatus": null,
    "startTime": null,
    "latitude": 33.09193,
    "longitude": -86.72224,
    "source": "https://kubra.io/cluster-data/232/5182a906-9bd4-45db-9507-dd11d2e3ae0c/019c7993-c647-4b35-bd91-98991348d802/public/cluster-1/03200232.json"
  },
  {
    "id": "2433788606",
    "etr": "2022-09-01T02:30:00Z",
    "etrConfidence": null,
    "cluster": false,
    "comments": "Field personnel have been assigned to evaluate the outage in your area. Your estimated repair time for this location is currently Aug 31, 2022, 9:30 PM Central. As the outage is evaluated, this message will be updated. ",
    "cause": null,
    "numberOut": 1,
    "custAffected": 4,
    "crewStatus": null,
    "startTime": null,
    "latitude": 31.897,
    "longitude": -87.04018,
    "source": "https://kubra.io/cluster-data/001/5182a906-9bd4-45db-9507-dd11d2e3ae0c/019c7993-c647-4b35-bd91-98991348d802/public/cluster-1/032020100.json"
  },
  {
    "id": "2433788607",
    "etr": "2022-09-01T02:30:00Z",
    "etrConfidence": null,
    "cluster": false,
    "comments": "We show your power is out at this location. Your estimated repair time is currently Aug 31, 2022, 9:30 PM Central. We are working to identify the problem.",
    "cause": null,
    "numberOut": 1,
    "custAffected": 4,
    "crewStatus": null,
    "startTime": null,
    "latitude": 31.94897,
    "longitude": -87.13087,
    "source": "https://kubra.io/cluster-data/001/5182a906-9bd4-45db-9507-dd11d2e3ae0c/019c7993-c647-4b35-bd91-98991348d802/public/cluster-1/032020100.json"
  },
  {
    "id": "2393781676",
    "etr": "2022-09-01T02:00:00Z",
    "etrConfidence": null,
    "cluster": false,
    "comments": "We show your power is out at this location. Your estimated repair time is currently Aug 31, 2022, 9:00 PM Central. We are working to identify the problem.",
    "cause": null,
    "numberOut": 1,
    "custAffected": 4,
    "crewStatus": null,
    "startTime": null,
    "latitude": 31.83206,
    "longitude": -86.61238,
    "source": "https://kubra.io/cluster-data/102/5182a906-9bd4-45db-9507-dd11d2e3ae0c/019c7993-c647-4b35-bd91-98991348d802/public/cluster-1/0320201.json"
  },
  {
    "id": "2433788571",
    "etr": "2022-09-01T23:30:00Z",
    "etrConfidence": null,
    "cluster": false,
    "comments": "We show your power is out at this location. Your estimated repair time is currently Sep 01, 2022, 6:30 PM Central. We are working to identify the problem.",
    "cause": null,
    "numberOut": 1,
    "custAffected": 4,
    "crewStatus": null,
    "startTime": null,
    "latitude": 31.17897,
    "longitude": -85.23918,
    "source": "https://kubra.io/cluster-data/102/5182a906-9bd4-45db-9507-dd11d2e3ae0c/019c7993-c647-4b35-bd91-98991348d802/public/cluster-1/0320201.json"
  },
  {
    "id": "2433788562",
    "etr": "2022-09-01T01:00:00Z",
    "etrConfidence": null,
    "cluster": false,
    "comments": "Field personnel are on their way to evaluate the outage in your area. Your estimated repair time for this location is currently Aug 31, 2022, 8:00 PM Central. As the outage is evaluated, this message will be updated.",
    "cause": null,
    "numberOut": 1,
    "custAffected": 4,
    "crewStatus": null,
    "startTime": null,
    "latitude": 32.52574,
    "longitude": -85.10681,
    "source": "https://kubra.io/cluster-data/320/5182a906-9bd4-45db-9507-dd11d2e3ae0c/019c7993-c647-4b35-bd91-98991348d802/public/cluster-1/0320023.json"
  },
  {
    "id": "2433788586",
    "etr": "2022-09-01T02:00:00Z",
    "etrConfidence": null,
    "cluster": false,
    "comments": "Field personnel are on their way to evaluate the outage in your area. Your estimated repair time for this location is currently Aug 31, 2022, 9:00 PM Central. As the outage is evaluated, this message will be updated.",
    "cause": null,
    "numberOut": 1,
    "custAffected": 4,
    "crewStatus": null,
    "startTime": null,
    "latitude": 30.57932,
    "longitude": -88.11178,
    "source": "https://kubra.io/cluster-data/030/5182a906-9bd4-45db-9507-dd11d2e3ae0c/019c7993-c647-4b35-bd91-98991348d802/public/cluster-1/032020030.json"
  },
  {
    "id": "2433788613",
    "etr": "2022-09-01T02:30:00Z",
    "etrConfidence": null,
    "cluster": false,
    "comments": "Field personnel have been assigned to evaluate the outage in your area. Your estimated repair time for this location is currently Aug 31, 2022, 9:30 PM Central. As the outage is evaluated, this message will be updated. ",
    "cause": null,
    "numberOut": 1,
    "custAffected": 108,
    "crewStatus": null,
    "startTime": null,
    "latitude": 30.59347,
    "longitude": -88.20556,
    "source": "https://kubra.io/cluster-data/030/5182a906-9bd4-45db-9507-dd11d2e3ae0c/019c7993-c647-4b35-bd91-98991348d802/public/cluster-1/032020030.json"
  }
]